clang_html/__init__.py
clang_html/__main__.py
clang_html/checks.py
clang_html/clang_visualizer.py
clang_html-1.6.1.dist-info/LICENSE
clang_html-1.6.1.dist-info/METADATA
clang_html-1.6.1.dist-info/WHEEL
clang_html-1.6.1.dist-info/entry_points.txt
clang_html-1.6.1.dist-info/top_level.txt
clang_html-1.6.1.dist-info/RECORD
