Metadata-Version: 2.1
Name: clang-html
Version: 1.6.1
Summary: Generates an html file that organizes your clang-tidy log output with the latest clang-tidy checks.
Home-page: https://github.com/austinbhale/Clang-Visualizer
Author: Austin Hale
Author-email: ah@unc.edu
License: MIT License
Keywords: clang,clang-tidy,html
Classifier: Programming Language :: Python :: 3
Classifier: License :: OSI Approved :: MIT License
Classifier: Operating System :: OS Independent
Requires-Python: >=3.6, <4
License-File: LICENSE
Requires-Dist: beautifulsoup4
Requires-Dist: certifi
Requires-Dist: lxml
Requires-Dist: requests
